ai_assignment_marker/AssignmentMarker.py
ai_assignment_marker/AssignmentsRunner.py
ai_assignment_marker/cli.py
ai_assignment_marker-0.1.0.dist-info/entry_points.txt
ai_assignment_marker-0.1.0.dist-info/METADATA
ai_assignment_marker-0.1.0.dist-info/WHEEL
ai_assignment_marker-0.1.0.dist-info/RECORD
