Metadata-Version: 2.1
Name: ai-assignment-marker
Version: 0.1.0
Summary: A marker that will use tests to run a cpp program and mark it based on the output. It will use the openAI api and LLMs to help process the output.
Home-page: https://github.com/1jamesthompson1/ai_assignment_marker
Author: James
Author-email: 1jamesthompson1@gmail.com
Requires-Python: >=3.11,<4.0
Classifier: Programming Language :: Python :: 3
Classifier: Programming Language :: Python :: 3.11
Requires-Dist: argparse (>=1.4.0,<2.0.0)
Requires-Dist: pytest (>=7.4.0,<8.0.0)
Project-URL: Repository, https://github.com/1jamesthompson1/ai_assignment_marker
